murnitur/__init__.py
murnitur/activation.py
murnitur/loaders.py
murnitur/main.py
murnitur/tracer.py
murnitur/util.py
murnitur/annotation/__init__.py
murnitur/annotation/eval.py
murnitur/annotation/knowledge_retention.py
murnitur/annotation/pii.py
murnitur/annotation/evaluation/__init__.py
murnitur/annotation/evaluation/_version.py
murnitur/annotation/evaluation/api.py
murnitur/annotation/evaluation/constants.py
murnitur/annotation/evaluation/evaluate.py
murnitur/annotation/evaluation/key_handler.py
murnitur/annotation/evaluation/progress_context.py
murnitur/annotation/evaluation/singleton.py
murnitur/annotation/evaluation/types.py
murnitur/annotation/evaluation/utils.py
murnitur/annotation/evaluation/dataset/__init__.py
murnitur/annotation/evaluation/dataset/api.py
murnitur/annotation/evaluation/dataset/dataset.py
murnitur/annotation/evaluation/dataset/golden.py
murnitur/annotation/evaluation/dataset/utils.py
murnitur/annotation/evaluation/integrations/__init__.py
murnitur/annotation/evaluation/integrations/harness/__init__.py
murnitur/annotation/evaluation/integrations/harness/callback.py
murnitur/annotation/evaluation/integrations/hugging_face/__init__.py
murnitur/annotation/evaluation/integrations/hugging_face/callback.py
murnitur/annotation/evaluation/integrations/hugging_face/rich_manager.py
murnitur/annotation/evaluation/integrations/hugging_face/utils.py
murnitur/annotation/evaluation/integrations/llama_index/__init__.py
murnitur/annotation/evaluation/integrations/llama_index/callback.py
murnitur/annotation/evaluation/integrations/llama_index/evaluators.py
murnitur/annotation/evaluation/integrations/llama_index/utils.py
murnitur/annotation/evaluation/metrics/__init__.py
murnitur/annotation/evaluation/metrics/base_metric.py
murnitur/annotation/evaluation/metrics/indicator.py
murnitur/annotation/evaluation/metrics/ragas.py
murnitur/annotation/evaluation/metrics/utils.py
murnitur/annotation/evaluation/metrics/answer_relevancy/__init__.py
murnitur-1.1.13.dist-info/METADATA
murnitur-1.1.13.dist-info/WHEEL
murnitur-1.1.13.dist-info/top_level.txt
murnitur-1.1.13.dist-info/RECORD
