Metadata-Version: 2.1
Name: murnitur
Version: 1.1.13
Summary: Murnitur empowers AI teams to seamlessly test, evaluate, deploy, monitor, and safeguard GenAI applications continuously.
Home-page: https://murnitur.ai
Author: Caleb Okpara
Author-email: support@murnitur.com
Requires-Python: >=3.7.1
Requires-Dist: requests
Requires-Dist: transformers (>=4.39.3)
Requires-Dist: pandas
Requires-Dist: vaderSentiment
Requires-Dist: openai
Requires-Dist: groq
Requires-Dist: anthropic
Requires-Dist: tqdm
Requires-Dist: pytest
Requires-Dist: tabulate
Requires-Dist: typer
Requires-Dist: rich
Requires-Dist: protobuf
Requires-Dist: pydantic
Requires-Dist: portalocker
Requires-Dist: langchain
Requires-Dist: langchain-core
Requires-Dist: langchain-openai
Requires-Dist: ragas
Requires-Dist: docx2txt (~=0.8)
Requires-Dist: importlib-metadata (>=6.0.2)
Requires-Dist: tenacity (~=8.2.3)
Requires-Dist: requests (>=2.26.0)
Requires-Dist: schedule (>=1.2.2)
Requires-Dist: tiktoken (>=0.7.0)
Requires-Dist: gpustat (>=1.1.1)
Requires-Dist: boto3 (>=1.34.0)
Requires-Dist: botocore (>=1.34.0)
Requires-Dist: opentelemetry-api (>=1.24.0)
Requires-Dist: opentelemetry-sdk (>=1.24.0)
Requires-Dist: opentelemetry-exporter-otlp (>=1.24.0)
Requires-Dist: opentelemetry-instrumentation (>=0.45b0)
